plasmasdk/__init__.py
plasmasdk/example.py
plasmasdk/sdk_v2.py
plasmasdk-1.0.2.dist-info/LICENSE
plasmasdk-1.0.2.dist-info/METADATA
plasmasdk-1.0.2.dist-info/WHEEL
plasmasdk-1.0.2.dist-info/top_level.txt
plasmasdk-1.0.2.dist-info/RECORD
