Metadata-Version: 2.1
Name: plasmasdk
Version: 1.0.2
Summary: Plasma Finance SDK
Home-page: https://www.ultrastiching.com/home
Author: Zhaolantao
Author-email: zhaolantao1995@163.com
License: MIT
Keywords: python,finance,sdk,api
Classifier: Development Status :: 4 - Beta
Classifier: License :: OSI Approved :: MIT License
Classifier: Programming Language :: Python :: 3.6
Classifier: Programming Language :: Python :: 3.7
Classifier: Programming Language :: Python :: 3.8
Classifier: Programming Language :: Python :: 3.9
Classifier: Programming Language :: Python :: 3.10
Classifier: Programming Language :: Python :: 3.11
Requires-Python: >=3.6
License-File: LICENSE
Requires-Dist: pandas
Requires-Dist: numpy
